TurtleMol/Box3D.py
TurtleMol/Sphere3D.py
TurtleMol/__init__.py
TurtleMol/__main__.py
TurtleMol/_version.py
TurtleMol/defaultParams.py
TurtleMol/drawMol.py
TurtleMol/isOverlap.py
TurtleMol/makeStruc.py
TurtleMol/mesh3D.py
TurtleMol/multMesh.py
TurtleMol/readWriteFiles.py
TurtleMol/setAtomProp.py
TurtleMol/shiftBox.py
TurtleMol/shiftDensity.py
TurtleMol/shiftHexagon.py
TurtleMol/shiftMesh.py
TurtleMol/shiftSphere.py
TurtleMol/shiftUnitCell.py
TurtleMol/surfaceNormal.py
TurtleMol/data/ElementData.csv
TurtleMol/data/__init__.py
TurtleMol-0.4.0.dist-info/LICENSE
TurtleMol-0.4.0.dist-info/METADATA
TurtleMol-0.4.0.dist-info/WHEEL
TurtleMol-0.4.0.dist-info/entry_points.txt
TurtleMol-0.4.0.dist-info/top_level.txt
TurtleMol-0.4.0.dist-info/RECORD
