Metadata-Version: 2.1
Name: TurtleMol
Version: 0.4.0
Summary: Design, create, and generate unique, complex molecular structures of any shape and size!
Author: Dominick Filonowich
Author-email: filonowichd74@gmail.com
Requires-Python: >=3.7
License-File: LICENSE
Requires-Dist: numpy
Requires-Dist: pandas
Requires-Dist: trimesh
Requires-Dist: rtree
Requires-Dist: scipy
Requires-Dist: pytest
